configloaders/__core.py
configloaders/__init__.py
configloaders/__main__.py
configloaders/__type.py
configloaders/providers/ini_provider.py
configloaders/providers/json_provider.py
configloaders/providers/pickle_provider.py
configloaders/providers/py_provider.py
configloaders/providers/toml_provider.py
configloaders/providers/txt_provider.py
configloaders/providers/xml_provider.py
configloaders/providers/yaml_provider.py
configloaders-2.2.2.dist-info/entry_points.txt
configloaders-2.2.2.dist-info/LICENSE
configloaders-2.2.2.dist-info/METADATA
configloaders-2.2.2.dist-info/WHEEL
configloaders-2.2.2.dist-info/RECORD
