Metadata-Version: 2.1
Name: configloaders
Version: 2.2.2
Summary: Configloaders is a Python library that allows you to easily load configuration from various types of configuration files and inject them into various types of objects, such as classes, dictionaries, functions, and methods.
Author: jawide
Author-email: 596929059@qq.com
Requires-Python: >=3.7,<4.0
Classifier: Programming Language :: Python :: 3
Classifier: Programming Language :: Python :: 3.7
Classifier: Programming Language :: Python :: 3.8
Classifier: Programming Language :: Python :: 3.9
Classifier: Programming Language :: Python :: 3.10
Classifier: Programming Language :: Python :: 3.11
